quart_events/__init__.py
quart_events/broker.py
quart_events/errors.py
quart_events/py.typed
quart_events/pytest_plugin.py
quart_events-0.4.3.dist-info/entry_points.txt
quart_events-0.4.3.dist-info/LICENSE
quart_events-0.4.3.dist-info/WHEEL
quart_events-0.4.3.dist-info/METADATA
quart_events-0.4.3.dist-info/RECORD
