Metadata-Version: 2.1
Name: quart-events
Version: 0.4.3
Summary: aquart extension to facilitate event message brokering
Home-page: https://github.com/smithk86/quart-events
License: MIT
Author: Kyle Smith
Author-email: smithk86@gmail.com
Requires-Python: >=3.8,<4.0
Classifier: Environment :: Web Environment
Classifier: Intended Audience :: Developers
Classifier: License :: OSI Approved :: MIT License
Classifier: Programming Language :: Python :: 3
Classifier: Programming Language :: Python :: 3.8
Classifier: Programming Language :: Python :: 3.9
Classifier: Programming Language :: Python :: 3.10
Classifier: Programming Language :: Python :: 3.11
Classifier: Topic :: Internet :: WWW/HTTP :: Dynamic Content
Classifier: Topic :: Software Development :: Libraries :: Python Modules
Requires-Dist: asyncio-multisubscriber-queue
Requires-Dist: quart
Project-URL: Repository, https://github.com/smithk86/quart-events
